libsnr/__init__.py
libsnr/version.py
libsnr/core/__init__.py
libsnr/core/arch.py
libsnr/core/common_paths.py
libsnr/core/logging.py
libsnr/core/options.py
libsnr/core/variable_manager.py
libsnr/payload/__init__.py
libsnr/payload/context.py
libsnr/payload/data_dir.py
libsnr/payload/safety_pin.py
libsnr/payload/storage.py
libsnr/payload/unix_group.py
libsnr/payload/unix_gshadow.py
libsnr/payload/unix_passwd.py
libsnr/payload/unix_shadow.py
libsnr/payload_generation/__init__.py
libsnr/payload_generation/common.py
libsnr/payload_generation/finishing.py
libsnr/payload_generation/formatting.py
libsnr/payload_generation/grub_installation.py
libsnr/payload_generation/partitioning.py
libsnr/payload_generation/rootfs_preparation.py
libsnr/payload_generation/satisfy_dependencies.py
libsnr/payload_generation/target_check.py
libsnr/util/__init__.py
libsnr/util/at_formatter.py
libsnr/util/chroot_program_wrapper.py
libsnr/util/coloring.py
libsnr/util/common_utils.py
libsnr/util/program_wrapper.py
libsnr/util/table.py
libsnr/util/payloads/__init__.py
libsnr/util/payloads/autorun.py
libsnr/util/payloads/libsnr.py
libsnr/util/payloads/systemd_networkd.py
libsnr/util/payloads/systemd_service.py
libsnr/util/payloads/systemd_target.py
libsnr/util/payloads/systemd_unit.py
libsnr/util/programs/__init__.py
libsnr/util/programs/debootstrap.py
libsnr/util/programs/mount.py
libsnr/util/programs/umount.py
libsnr-0.1.0.dist-info/LICENSE
libsnr-0.1.0.dist-info/METADATA
libsnr-0.1.0.dist-info/WHEEL
libsnr-0.1.0.dist-info/top_level.txt
libsnr-0.1.0.dist-info/RECORD
