Metadata-Version: 2.1
Name: libsnr
Version: 0.1.0
Summary: Generate bootable payloads easily - Library
Home-page: https://github.com/GlobularOne/libsnr
Author: Kamyar Hatamnezhad (GlobularOne)
Author-email: GlobularOne@proton.me
License: Apache-2.0
Requires-Python: >=3.10
License-File: LICENSE
